Metadata-Version: 2.1
Name: example-package-jack
Version: 0.0.1
Summary: my first package
Author-email: jacki chan <uwannacry1@gmail.com>
License: Copyright (c) 2018 The Python Packaging Authority        
Project-URL: Homepage, https://do-u-wanna-cry.com
Project-URL: Bug Tracker, https://i-c-u-do.com
Classifier: Programming Language :: Python :: 3
Classifier: License :: OSI Approved :: MIT License
Classifier: Operating System :: OS Independent
Requires-Python: >=3.7
License-File: LICENSE
